{
  "timestamp": "2025-12-29T02:07:48.914661",
  "developers": [
    {
      "name": "Weave-MC",
      "projects": [
        {
          "name": "ExampleMod",
          "repository": "Weave-MC/ExampleMod",
          "url": "https://github.com/Weave-MC/ExampleMod",
          "description": null,
          "newWeave": true
        },
        {
          "name": "Weave-Loader",
          "repository": "Weave-MC/Weave-Loader",
          "url": "https://github.com/Weave-MC/Weave-Loader",
          "description": "Universal Minecraft Client Mod-Loader, written in Kotlin",
          "newWeave": true
        }
      ]
    },
    {
      "name": "Tryflle",
      "projects": [
        {
          "name": "LegacyEvents",
          "repository": "Tryflle/LegacyEvents",
          "url": "https://github.com/Tryflle/LegacyEvents",
          "description": "Lib for Weave 1.0",
          "newWeave": true
        },
        {
          "name": "RawInput-Weave",
          "repository": "Tryflle/RawInput-Weave",
          "url": "https://github.com/Tryflle/RawInput-Weave",
          "description": "Directly handles input from the mouse.",
          "newWeave": true
        },
        {
          "name": "WeaveNoJumpDelay",
          "repository": "Tryflle/WeaveNoJumpDelay",
          "url": "https://github.com/Tryflle/WeaveNoJumpDelay",
          "description": "simple njd mod for weave",
          "newWeave": true
        },
        {
          "name": "WeaveToggleSprint",
          "repository": "Tryflle/WeaveToggleSprint",
          "url": "https://github.com/Tryflle/WeaveToggleSprint",
          "description": null,
          "newWeave": true
        },
        {
          "name": "WeaveChamsMod",
          "repository": "Tryflle/WeaveChamsMod",
          "url": "https://github.com/Tryflle/WeaveChamsMod",
          "description": "Chams!",
          "newWeave": false
        },
        {
          "name": "ktlon",
          "repository": "Tryflle/ktlon",
          "url": "https://github.com/Tryflle/ktlon",
          "description": "omg ktlon",
          "newWeave": false
        },
        {
          "name": "InventorySnow",
          "repository": "Tryflle/InventorySnow",
          "url": "https://github.com/Tryflle/InventorySnow",
          "description": "InventorySnow",
          "newWeave": false
        },
        {
          "name": "WeaveShortcuts",
          "repository": "Tryflle/WeaveShortcuts",
          "url": "https://github.com/Tryflle/WeaveShortcuts",
          "description": "Make command shortcuts",
          "newWeave": false
        },
        {
          "name": "WeaveQuickReport",
          "repository": "Tryflle/WeaveQuickReport",
          "url": "https://github.com/Tryflle/WeaveQuickReport",
          "description": "QuickReport (https://github.com/varun7654/QuickReport/) rewritten for weave. Also comes with autododge.",
          "newWeave": false
        },
        {
          "name": "WeaveSlowMining",
          "repository": "Tryflle/WeaveSlowMining",
          "url": "https://github.com/Tryflle/WeaveSlowMining",
          "description": "A mod that slows down your swing/mining animation that can be configurated.",
          "newWeave": false
        },
        {
          "name": "CPSCap",
          "repository": "Tryflle/CPSCap",
          "url": "https://github.com/Tryflle/CPSCap",
          "description": "A mod that caps your CPS.",
          "newWeave": false
        }
      ]
    },
    {
      "name": "astraltweaks",
      "projects": [
        {
          "name": "NoHitDelay",
          "repository": "astraltweaks/NoHitDelay",
          "url": "https://github.com/astraltweaks/NoHitDelay",
          "description": "NoHitDelay is a weave mod that removes the 1.8.9 hit penalty but can be toggled off and on with commands.",
          "newWeave": true
        }
      ]
    },
    {
      "name": "douzooo",
      "projects": [
        {
          "name": "NovaX_Dev",
          "repository": "douzooo/NovaX_Dev",
          "url": "https://github.com/douzooo/NovaX_Dev",
          "description": null,
          "newWeave": true
        }
      ]
    },
    {
      "name": "exejar",
      "projects": [
        {
          "name": "Seraph",
          "repository": "exejar/Seraph",
          "url": "https://github.com/exejar/Seraph",
          "description": "Statistic Weave Mod for Hypixel",
          "newWeave": false
        },
        {
          "name": "PlayerScreenshot",
          "repository": "exejar/PlayerScreenshot",
          "url": "https://github.com/exejar/PlayerScreenshot",
          "description": "Weave mod that takes screenshots of only your player",
          "newWeave": false
        },
        {
          "name": "Kolour",
          "repository": "exejar/Kolour",
          "url": "https://github.com/exejar/Kolour",
          "description": "Simple, Powerful, and Performant GUI Library for Minecraft",
          "newWeave": false
        },
        {
          "name": "Weave",
          "repository": "exejar/Weave",
          "url": "https://github.com/exejar/Weave",
          "description": "Weave API",
          "newWeave": false
        },
        {
          "name": "WeaveYouTube",
          "repository": "exejar/WeaveYouTube",
          "url": "https://github.com/exejar/WeaveYouTube",
          "description": "YouTube showcase on Weave and how it can be used to create a simple 2D ESP in Minecraft.",
          "newWeave": false
        },
        {
          "name": "WeaveClientTemplate",
          "repository": "exejar/WeaveClientTemplate",
          "url": "https://github.com/exejar/WeaveClientTemplate",
          "description": "Minecraft Utility Client Template for Weave written in Kotlin",
          "newWeave": false
        }
      ]
    },
    {
      "name": "Legitish",
      "projects": [
        {
          "name": "Legit-ish",
          "repository": "Legitish/Legit-ish",
          "url": "https://github.com/Legitish/Legit-ish",
          "description": "Mixin-based utility mod for the Weave modbase.",
          "newWeave": false
        }
      ]
    },
    {
      "name": "ZirctaWeave",
      "projects": [
        {
          "name": "AlwaysSwing",
          "repository": "ZirctaWeave/AlwaysSwing",
          "url": "https://github.com/ZirctaWeave/AlwaysSwing",
          "description": null,
          "newWeave": false
        },
        {
          "name": "ToggleChat",
          "repository": "ZirctaWeave/ToggleChat",
          "url": "https://github.com/ZirctaWeave/ToggleChat",
          "description": null,
          "newWeave": false
        },
        {
          "name": "Crow",
          "repository": "ZirctaWeave/Crow",
          "url": "https://github.com/ZirctaWeave/Crow",
          "description": null,
          "newWeave": false
        },
        {
          "name": "AntiAntiAgent",
          "repository": "ZirctaWeave/AntiAntiAgent",
          "url": "https://github.com/ZirctaWeave/AntiAntiAgent",
          "description": null,
          "newWeave": false
        },
        {
          "name": "NoItemRelease",
          "repository": "ZirctaWeave/NoItemRelease",
          "url": "https://github.com/ZirctaWeave/NoItemRelease",
          "description": null,
          "newWeave": false
        },
        {
          "name": "stormy",
          "repository": "ZirctaWeave/stormy",
          "url": "https://github.com/ZirctaWeave/stormy",
          "description": null,
          "newWeave": false
        },
        {
          "name": "ProjectileTrails",
          "repository": "ZirctaWeave/ProjectileTrails",
          "url": "https://github.com/ZirctaWeave/ProjectileTrails",
          "description": null,
          "newWeave": false
        }
      ]
    },
    {
      "name": "cranci1",
      "projects": [
        {
          "name": "Stormy",
          "repository": "cranci1/Stormy",
          "url": "https://github.com/cranci1/Stormy",
          "description": "A weave utility client",
          "newWeave": false
        }
      ]
    },
    {
      "name": "supercoolspy",
      "projects": [
        {
          "name": "PitUtilsLunar",
          "repository": "supercoolspy/PitUtilsLunar",
          "url": "https://github.com/supercoolspy/PitUtilsLunar",
          "description": null,
          "newWeave": false
        }
      ]
    },
    {
      "name": "TianmuTNT",
      "projects": [
        {
          "name": "mm-utils-cn",
          "repository": "TianmuTNT/mm-utils-cn",
          "url": "https://github.com/TianmuTNT/mm-utils-cn",
          "description": "[Hypixel Murder Mystery \u5bc6\u5ba4\u6740\u624b] mm-utils\u7684\u6c49\u5316\u7248\uff0c\u4fee\u590d\u4e86\u539f\u7248\u7684\u4e00\u4e9b\u95ee\u9898",
          "newWeave": false
        }
      ]
    },
    {
      "name": "PianoPenguin471",
      "projects": [
        {
          "name": "RavenWeaveLite",
          "repository": "PianoPenguin471/RavenWeaveLite",
          "url": "https://github.com/PianoPenguin471/RavenWeaveLite",
          "description": null,
          "newWeave": false
        },
        {
          "name": "SessionLogin",
          "repository": "PianoPenguin471/SessionLogin",
          "url": "https://github.com/PianoPenguin471/SessionLogin",
          "description": "Lets you login to Minecraft with a session Id. WIP",
          "newWeave": false
        }
      ]
    },
    {
      "name": "Oery",
      "projects": [
        {
          "name": "super-who",
          "repository": "Oery/super-who",
          "url": "https://github.com/Oery/super-who",
          "description": "A Weave mod that let you list all players in tab and put it into chat.",
          "newWeave": false
        },
        {
          "name": "NoBridgeBobbing-Weave",
          "repository": "Oery/NoBridgeBobbing-Weave",
          "url": "https://github.com/Oery/NoBridgeBobbing-Weave",
          "description": "A Minecraft Weave Mod to disable ViewBobbing when bridging",
          "newWeave": false
        }
      ]
    },
    {
      "name": "svxf",
      "projects": [
        {
          "name": "HealthIndicator",
          "repository": "svxf/HealthIndicator",
          "url": "https://github.com/svxf/HealthIndicator",
          "description": null,
          "newWeave": false
        },
        {
          "name": "LegitVisuals",
          "repository": "svxf/LegitVisuals",
          "url": "https://github.com/svxf/LegitVisuals",
          "description": null,
          "newWeave": false
        }
      ]
    },
    {
      "name": "ballmc",
      "projects": [
        {
          "name": "barriervisibility",
          "repository": "ballmc/barriervisibility",
          "url": "https://github.com/ballmc/barriervisibility",
          "description": "Weave Minecraft mod that allows you to see invisible barrier blocks.",
          "newWeave": false
        }
      ]
    },
    {
      "name": "SleepyFish-YT",
      "projects": [
        {
          "name": "Weave-Example-Mod",
          "repository": "SleepyFish-YT/Weave-Example-Mod",
          "url": "https://github.com/SleepyFish-YT/Weave-Example-Mod",
          "description": "This is a weave mod example theres nothing exciting about it tho.",
          "newWeave": false
        },
        {
          "name": "Smok",
          "repository": "SleepyFish-YT/Smok",
          "url": "https://github.com/SleepyFish-YT/Smok",
          "description": "A good and one of the first Weave ghost clients",
          "newWeave": false
        }
      ]
    },
    {
      "name": "L1shed",
      "projects": [
        {
          "name": "WNC",
          "repository": "L1shed/WNC",
          "url": "https://github.com/L1shed/WNC",
          "description": "Minecraft hacked client for Lunar Client using Weave, written in Kotlin",
          "newWeave": false
        }
      ]
    },
    {
      "name": "NatselCat",
      "projects": [
        {
          "name": "WeavePeacefulMining",
          "repository": "NatselCat/WeavePeacefulMining",
          "url": "https://github.com/NatselCat/WeavePeacefulMining",
          "description": "Weave Loader recreation of Cosmic Client's peaceful mining feature.",
          "newWeave": false
        }
      ]
    },
    {
      "name": "Youded-byte",
      "projects": [
        {
          "name": "unrestricted",
          "repository": "Youded-byte/unrestricted",
          "url": "https://github.com/Youded-byte/unrestricted",
          "description": null,
          "newWeave": false
        }
      ]
    },
    {
      "name": "azureskylines",
      "projects": [
        {
          "name": "Velvet",
          "repository": "azureskylines/Velvet",
          "url": "https://github.com/azureskylines/Velvet",
          "description": "It's something alright.",
          "newWeave": false
        }
      ]
    },
    {
      "name": "JavaSkid",
      "projects": [
        {
          "name": "Compass",
          "repository": "JavaSkid/Compass",
          "url": "https://github.com/JavaSkid/Compass",
          "description": "Idk",
          "newWeave": false
        }
      ]
    },
    {
      "name": "MolokyMC",
      "projects": [
        {
          "name": "WiltLunar",
          "repository": "MolokyMC/WiltLunar",
          "url": "https://github.com/MolokyMC/WiltLunar",
          "description": "PacketFixer in HuaYuTing Server",
          "newWeave": false
        }
      ]
    },
    {
      "name": "imyanice",
      "projects": [
        {
          "name": "mm-utils",
          "repository": "imyanice/mm-utils",
          "url": "https://github.com/imyanice/mm-utils",
          "description": "A Hypixel Murder Mystery Utilities Weave mod (Lunar Client compatible).",
          "newWeave": false
        }
      ]
    },
    {
      "name": "Jimin69",
      "projects": [
        {
          "name": "MinecraftPwetUtils",
          "repository": "Jimin69/MinecraftPwetUtils",
          "url": "https://github.com/Jimin69/MinecraftPwetUtils",
          "description": "Minecraft Personal Utilities mod using Weave API to use on restricted/locked down clients.",
          "newWeave": false
        }
      ]
    },
    {
      "name": "1lylily",
      "projects": [
        {
          "name": "LilysQoLMod",
          "repository": "1lylily/LilysQoLMod",
          "url": "https://github.com/1lylily/LilysQoLMod",
          "description": "\"Quality of Life\" Weave Loader mod.",
          "newWeave": false
        },
        {
          "name": "coc-banana",
          "repository": "1lylily/coc-banana",
          "url": "https://github.com/1lylily/coc-banana",
          "description": null,
          "newWeave": false
        }
      ]
    },
    {
      "name": "solsahar",
      "projects": [
        {
          "name": "Twitch-Chat-In-Game",
          "repository": "solsahar/Twitch-Chat-In-Game",
          "url": "https://github.com/solsahar/Twitch-Chat-In-Game",
          "description": null,
          "newWeave": false
        }
      ]
    }
  ]
}